{
 "data": [
  {
   "height": 200,
   "name": "IMG0900A.jpg",
   "width": 150
  },
  {
   "height": 200,
   "name": "IMG0081A (2).jpg",
   "width": 150
  },
  {
   "height": 200,
   "name": "IMG0148A.jpg",
   "width": 266
  },
  {
   "height": 200,
   "name": "IMG0774A.jpg",
   "width": 266
  },
  {
   "height": 200,
   "name": "IMG0467B.jpg",
   "width": 150
  },
  {
   "height": 200,
   "name": "IMG0198A (2).jpg",
   "width": 150
  },
  {
   "height": 200,
   "name": "IMG0320B.jpg",
   "width": 150
  },
  {
   "height": 200,
   "name": "IMG0207A.jpg",
   "width": 266
  },
  {
   "height": 200,
   "name": "IMG0099A (2).jpg",
   "width": 150
  },
  {
   "height": 200,
   "name": "IMG0013A (2).jpg",
   "width": 150
  },
  {
   "height": 200,
   "name": "IMG0197B.jpg",
   "width": 150
  },
  {
   "height": 200,
   "name": "IMG0403A.jpg",
   "width": 150
  },
  {
   "height": 200,
   "name": "IMG0834A.jpg",
   "width": 150
  },
  {
   "height": 200,
   "name": "IMG_20190815_150942.jpg",
   "width": 266
  },
  {
   "height": 200,
   "name": "IMG0175A (2).jpg",
   "width": 150
  },
  {
   "height": 200,
   "name": "IMG0106A.jpg",
   "width": 266
  },
  {
   "height": 200,
   "name": "IMG_20150821_194521.jpg",
   "width": 150
  },
  {
   "height": 200,
   "name": "IMG_20190503_173655.jpg",
   "width": 356
  },
  {
   "height": 200,
   "name": "IMG0418B.jpg",
   "width": 150
  },
  {
   "height": 200,
   "name": "IMG_20150605_211255.jpg",
   "width": 266
  },
  {
   "height": 200,
   "name": "IMG_20190320_210315.jpg",
   "width": 356
  },
  {
   "height": 200,
   "name": "IMG0255B.jpg",
   "width": 150
  },
  {
   "height": 200,
   "name": "IMG0345B.jpg",
   "width": 150
  },
  {
   "height": 200,
   "name": "IMG0065B.jpg",
   "width": 150
  },
  {
   "height": 200,
   "name": "IMG0453B.jpg",
   "width": 266
  },
  {
   "height": 200,
   "name": "IMG0212B.jpg",
   "width": 266
  },
  {
   "height": 200,
   "name": "IMG_20190817_144151.jpg",
   "width": 266
  },
  {
   "height": 200,
   "name": "IMG0401B.jpg",
   "width": 150
  },
  {
   "height": 200,
   "name": "20120814232.jpg",
   "width": 266
  },
  {
   "height": 200,
   "name": "IMG0078C.jpg",
   "width": 266
  },
  {
   "height": 200,
   "name": "IMG0003A (3).jpg",
   "width": 150
  },
  {
   "height": 200,
   "name": "IMG0069B.jpg",
   "width": 150
  },
  {
   "height": 200,
   "name": "IMG0645B.jpg",
   "width": 266
  },
  {
   "height": 200,
   "name": "IMG_20171231_135551.jpg",
   "width": 356
  },
  {
   "height": 200,
   "name": "IMG_20150803_181758.jpg",
   "width": 150
  },
  {
   "height": 200,
   "name": "IMG1006A.jpg",
   "width": 150
  },
  {
   "height": 200,
   "name": "IMG0400A.jpg",
   "width": 150
  },
  {
   "height": 200,
   "name": "IMG0047A (2).jpg",
   "width": 266
  },
  {
   "height": 200,
   "name": "IMG0549A.jpg",
   "width": 266
  },
  {
   "height": 200,
   "name": "IMG0090C.jpg",
   "width": 150
  },
  {
   "height": 200,
   "name": "IMG0267A.jpg",
   "width": 266
  },
  {
   "height": 200,
   "name": "IMG0218A.jpg",
   "width": 266
  },
  {
   "height": 200,
   "name": "IMG0043B.jpg",
   "width": 150
  },
  {
   "height": 200,
   "name": "IMG0067A.jpg",
   "width": 266
  },
  {
   "height": 200,
   "name": "20120710194.jpg",
   "width": 266
  },
  {
   "height": 200,
   "name": "IMG_20190619_071925.jpg",
   "width": 266
  },
  {
   "height": 200,
   "name": "IMG0633A.jpg",
   "width": 150
  },
  {
   "height": 200,
   "name": "IMG0248C.jpg",
   "width": 266
  },
  {
   "height": 200,
   "name": "IMG0400B.jpg",
   "width": 266
  },
  {
   "height": 200,
   "name": "IMG0668A.jpg",
   "width": 266
  },
  {
   "height": 200,
   "name": "IMG0640A.jpg",
   "width": 150
  },
  {
   "height": 200,
   "name": "IMG0341B.jpg",
   "width": 150
  },
  {
   "height": 200,
   "name": "IMG0115A.jpg",
   "width": 266
  },
  {
   "height": 200,
   "name": "IMG0474A.jpg",
   "width": 150
  },
  {
   "height": 200,
   "name": "IMG0244B.jpg",
   "width": 266
  },
  {
   "height": 200,
   "name": "IMG0998A.jpg",
   "width": 266
  },
  {
   "height": 200,
   "name": "IMG0372A.jpg",
   "width": 150
  },
  {
   "height": 200,
   "name": "IMG0061C.jpg",
   "width": 150
  },
  {
   "height": 200,
   "name": "IMG0766A.jpg",
   "width": 150
  },
  {
   "height": 200,
   "name": "IMG0086A.jpg",
   "width": 266
  },
  {
   "height": 200,
   "name": "IMG0153A.jpg",
   "width": 266
  },
  {
   "height": 200,
   "name": "IMG0382A.jpg",
   "width": 150
  },
  {
   "height": 200,
   "name": "IMG0141A.jpg",
   "width": 150
  },
  {
   "height": 200,
   "name": "IMG0407B.jpg",
   "width": 150
  },
  {
   "height": 200,
   "name": "IMG0396A.jpg",
   "width": 150
  },
  {
   "height": 200,
   "name": "IMG0620B.jpg",
   "width": 150
  },
  {
   "height": 200,
   "name": "IMG0201B.jpg",
   "width": 266
  },
  {
   "height": 200,
   "name": "IMG0137A.jpg",
   "width": 150
  },
  {
   "height": 200,
   "name": "IMG0998B.jpg",
   "width": 150
  },
  {
   "height": 200,
   "name": "IMG_20171226_082627.jpg",
   "width": 112
  },
  {
   "height": 200,
   "name": "IMG0010A.jpg",
   "width": 150
  },
  {
   "height": 200,
   "name": "IMG0094D.jpg",
   "width": 150
  },
  {
   "height": 200,
   "name": "IMG_20171109_223058.jpg",
   "width": 356
  },
  {
   "height": 200,
   "name": "IMG_20190623_111302.jpg",
   "width": 266
  },
  {
   "height": 200,
   "name": "IMG0193A.jpg",
   "width": 266
  },
  {
   "height": 200,
   "name": "IMG_20150623_175526.jpg",
   "width": 266
  },
  {
   "height": 200,
   "name": "IMG20170805124004.jpg",
   "width": 342
  },
  {
   "height": 200,
   "name": "IMG_20150802_220628.jpg",
   "width": 266
  },
  {
   "height": 200,
   "name": "IMG0050A.jpg",
   "width": 150
  },
  {
   "height": 200,
   "name": "IMG0294A.jpg",
   "width": 266
  },
  {
   "height": 200,
   "name": "IMG0750A.jpg",
   "width": 150
  },
  {
   "height": 200,
   "name": "IMG0422B.jpg",
   "width": 150
  },
  {
   "height": 200,
   "name": "IMG0631B.jpg",
   "width": 266
  },
  {
   "height": 200,
   "name": "IMG0712B.jpg",
   "width": 150
  },
  {
   "height": 200,
   "name": "IMG0071A (2).jpg",
   "width": 266
  },
  {
   "height": 200,
   "name": "IMG0488B.jpg",
   "width": 266
  },
  {
   "height": 200,
   "name": "IMG_20150628_223852.jpg",
   "width": 266
  },
  {
   "height": 200,
   "name": "IMG0595A.jpg",
   "width": 150
  },
  {
   "height": 200,
   "name": "IMG0025A.jpg",
   "width": 150
  },
  {
   "height": 200,
   "name": "IMG0912B.jpg",
   "width": 150
  },
  {
   "height": 200,
   "name": "IMG0221A.jpg",
   "width": 266
  },
  {
   "height": 200,
   "name": "IMG0519A.jpg",
   "width": 150
  },
  {
   "height": 200,
   "name": "IMG_20150810_175147.jpg",
   "width": 150
  },
  {
   "height": 200,
   "name": "IMG0824A.jpg",
   "width": 150
  },
  {
   "height": 200,
   "name": "IMG0837A.jpg",
   "width": 150
  },
  {
   "height": 200,
   "name": "IMG0494A.jpg",
   "width": 150
  },
  {
   "height": 200,
   "name": "IMG0375A.jpg",
   "width": 150
  },
  {
   "height": 200,
   "name": "IMG0696A.jpg",
   "width": 150
  },
  {
   "height": 200,
   "name": "IMG_20150808_192740.jpg",
   "width": 266
  },
  {
   "height": 200,
   "name": "IMG0809A.jpg",
   "width": 150
  }
 ]
}